CHANGES.txt
LICENSE.txt
MANIFEST.in
README.txt
setup.py
src/j01/__init__.py
src/j01.tree.egg-info/PKG-INFO
src/j01.tree.egg-info/SOURCES.txt
src/j01.tree.egg-info/dependency_links.txt
src/j01.tree.egg-info/namespace_packages.txt
src/j01.tree.egg-info/not-zip-safe
src/j01.tree.egg-info/requires.txt
src/j01.tree.egg-info/top_level.txt
src/j01/tree/__init__.py
src/j01/tree/base.py
src/j01/tree/browser.py
src/j01/tree/browser.zcml
src/j01/tree/configure.zcml
src/j01/tree/interfaces.py
src/j01/tree/jsonrpc.py
src/j01/tree/jsonrpc.zcml
src/j01/tree/li.pt
src/j01/tree/tree.pt
src/j01/tree/ul.pt
src/j01/tree/util.py
src/j01/tree/css/j01.tree.css
src/j01/tree/img/j01TreeCollapsed.gif
src/j01/tree/img/j01TreeExpanded.gif
src/j01/tree/img/j01TreeStatic.gif
src/j01/tree/js/j01.tree.js
src/j01/tree/tests/__init__.py
src/j01/tree/tests/checker.txt
src/j01/tree/tests/tests.py